Metadata-Version: 2.1
Name: traitlite
Version: 0.0.3
Summary: A light-weight module that aims to provide control for class attributes.
Home-page: https://github.com/lejar/traitlite
Author: Christopher Pezley
Author-email: pypi@pezley.net
License: UNKNOWN
Platform: UNKNOWN
Classifier: Programming Language :: Python :: 3
Classifier: License :: OSI Approved :: MIT License
Classifier: Operating System :: OS Independent
